mcstats/__init__.py
mcstats/main.py
mcstats/lib/__init__.py
mcstats/lib/packet.py
mcstats/lib/raknet.py
mcstats-0.0.1.dist-info/LICENSE
mcstats-0.0.1.dist-info/METADATA
mcstats-0.0.1.dist-info/WHEEL
mcstats-0.0.1.dist-info/entry_points.txt
mcstats-0.0.1.dist-info/top_level.txt
mcstats-0.0.1.dist-info/RECORD
